src/4_bit_counter.v
module counter_4bit (
    input  wire        clk,
    input  wire        rst_n,   // active-low async reset
    input  wire        enable,
    output reg  [3:0]  count
);

    always @(posedge clk or negedge rst_n) begin
        if (!rst_n)
            count <= 4'b0000;
        else if (enable)
            count <= count + 1;
    end

endmodule

src/4_bit_counter_tb.v
`timescale 1ns/1ps

module tb_counter_4bit;

    // -------------------------------------------------------
    // DUT signals
    // -------------------------------------------------------
    reg        clk;
    reg        rst_n;
    reg        enable;
    wire [3:0] count;

    integer errors = 0;

    // -------------------------------------------------------
    // DUT instantiation
    // -------------------------------------------------------
    counter_4bit dut (
        .clk    (clk),
        .rst_n  (rst_n),
        .enable (enable),
        .count  (count)
    );

    // -------------------------------------------------------
    // Clock generation - 10ns period = 100MHz
    // -------------------------------------------------------
    initial clk = 0;
    always #5 clk = ~clk;

    // -------------------------------------------------------
    // Task: apply reset
    // -------------------------------------------------------
    task apply_reset;
        begin
            rst_n = 0;
            @(posedge clk); #1;
            @(posedge clk); #1;
            if (count !== 4'b0000) begin
                $display("FAIL: reset -- expected count=0, got count=%0d", count);
                errors = errors + 1;
            end else begin
                $display("PASS: reset holds count at 0");
            end
            rst_n = 1; // release reset
        end
    endtask

    // -------------------------------------------------------
    // Task: check count increments correctly for N cycles
    // -------------------------------------------------------
    task check_increment;
        input integer cycles;
        integer i;
        reg [3:0] expected;
        begin
            expected = count; // start from current count value
            for (i = 0; i < cycles; i = i + 1) begin
                expected = expected + 1; // 4-bit overflow wraps naturally
                @(posedge clk); #1;
                if (count !== expected) begin
                    $display("FAIL: increment -- expected count=%0d, got count=%0d at cycle %0d",
                              expected, count, i);
                    errors = errors + 1;
                end else begin
                    $display("PASS: count=%0d correct", count);
                end
            end
        end
    endtask

    // -------------------------------------------------------
    // Task: check count freezes when enable=0
    // -------------------------------------------------------
    task check_enable_freeze;
        input integer cycles;
        integer i;
        reg [3:0] frozen_val;
        begin
            enable     = 0;
            frozen_val = count;
            for (i = 0; i < cycles; i = i + 1) begin
                @(posedge clk); #1;
                if (count !== frozen_val) begin
                    $display("FAIL: enable=0 -- count changed to %0d, should stay at %0d",
                              count, frozen_val);
                    errors = errors + 1;
                end else begin
                    $display("PASS: enable=0, count frozen at %0d", count);
                end
            end
            enable = 1; // re-enable after freeze test
        end
    endtask

    // -------------------------------------------------------
    // Task: async reset mid-count
    // -------------------------------------------------------
    task check_async_reset;
        begin
            // let it count a few cycles first
            @(posedge clk); #1;
            @(posedge clk); #1;
            // assert reset mid-stream (NOT on a clock edge - async!)
            #3; // mid-cycle, 3ns after last posedge
            rst_n = 0;
            #1;
            if (count !== 4'b0000) begin
                $display("FAIL: async reset -- count should be 0 immediately, got %0d", count);
                errors = errors + 1;
            end else begin
                $display("PASS: async reset forced count to 0 immediately (no clock edge needed)");
            end
            @(posedge clk); #1;
            rst_n = 1;
        end
    endtask

    // -------------------------------------------------------
    // Task: wrap-around check (count 0->15->0)
    // -------------------------------------------------------
    task check_wraparound;
        integer i;
        reg [3:0] expected;
        begin
            // reset first to get to a known state
            rst_n    = 0;
            @(posedge clk); #1;
            rst_n    = 1;
            enable   = 1;
            expected = 0;
            // count all 16 values and check wrap
            for (i = 0; i < 17; i = i + 1) begin
                @(posedge clk); #1;
                expected = expected + 1;
                if (count !== expected[3:0]) begin
                    $display("FAIL: wraparound at i=%0d -- expected %0d got %0d",
                              i, expected[3:0], count);
                    errors = errors + 1;
                end else begin
                    $display("PASS: wraparound check count=%0d", count);
                end
            end
        end
    endtask

    // -------------------------------------------------------
    // Main test sequence
    // -------------------------------------------------------
    initial begin
        $dumpfile("counter_tb.vcd");
        $dumpvars(0, tb_counter_4bit);

        // initialise
        rst_n  = 0;
        enable = 0;
        clk    = 0;

        repeat(3) @(posedge clk);

        $display("\n--- Test 1: Reset ---");
        apply_reset;

        $display("\n--- Test 2: Count up 8 cycles ---");
        enable = 1;
        check_increment(8);

        $display("\n--- Test 3: Enable freeze ---");
        check_enable_freeze(3);

        $display("\n--- Test 4: Async reset mid-count ---");
        check_async_reset;

        $display("\n--- Test 5: Full wrap-around (0 to 15 to 0) ---");
        check_wraparound;

        // ---- Summary ----
        $display("\n=========================================");
        $display(" ERRORS : %0d", errors);
        if (errors == 0)
            $display(" RESULT : ALL TESTS PASSED");
        else
            $display(" RESULT : FAILED");
        $display("=========================================\n");

        #50;
        $finish;
    end

endmodule

docs/counter_tb.vcd
$date
	Sun Jun 28 20:00:45 2026
$end
$version
	Icarus Verilog
$end
$timescale
	1ps
$end
$scope module tb_counter_4bit $end
$var wire 4 ! count [3:0] $end
$var reg 1 " clk $end
$var reg 1 # enable $end
$var reg 1 $ rst_n $end
$var integer 32 % errors [31:0] $end
$scope module dut $end
$var wire 1 " clk $end
$var wire 1 # enable $end
$var wire 1 $ rst_n $end
$var reg 4 & count [3:0] $end
$upscope $end
$scope task apply_reset $end
$upscope $end
$scope task check_async_reset $end
$upscope $end
$scope task check_enable_freeze $end
$var reg 4 ' frozen_val [3:0] $end
$var integer 32 ( cycles [31:0] $end
$var integer 32 ) i [31:0] $end
$upscope $end
$scope task check_increment $end
$var reg 4 * expected [3:0] $end
$var integer 32 + cycles [31:0] $end
$var integer 32 , i [31:0] $end
$upscope $end
$scope task check_wraparound $end
$var reg 4 - expected [3:0] $end
$var integer 32 . i [31:0] $end
$upscope $end
$upscope $end
$enddefinitions $end
#0
$dumpvars
bx .
bx -
bx ,
bx +
bx *
bx )
bx (
bx '
b0 &
b0 %
0$
0#
0"
b0 !
$end
#5000
1"
#10000
0"
#15000
1"
#20000
0"
#25000
1"
#30000
0"
#35000
1"
#40000
0"
#45000
1"
#46000
b0 ,
b1 *
b1000 +
1#
1$
#50000
0"
#55000
b1 !
b1 &
1"
#56000
b10 *
b1 ,
#60000
0"
#65000
b10 !
b10 &
1"
#66000
b11 *
b10 ,
#70000
0"
#75000
b11 !
b11 &
1"
#76000
b100 *
b11 ,
#80000
0"
#85000
b100 !
b100 &
1"
#86000
b101 *
b100 ,
#90000
0"
#95000
b101 !
b101 &
1"
#96000
b110 *
b101 ,
#100000
0"
#105000
b110 !
b110 &
1"
#106000
b111 *
b110 ,
#110000
0"
#115000
b111 !
b111 &
1"
#116000
b1000 *
b111 ,
#120000
0"
#125000
b1000 !
b1000 &
1"
#126000
b0 )
b1000 '
0#
b11 (
b1000 ,
#130000
0"
#135000
1"
#136000
b1 )
#140000
0"
#145000
1"
#146000
b10 )
#150000
0"
#155000
1"
#156000
1#
b11 )
#160000
0"
#165000
b1001 !
b1001 &
1"
#170000
0"
#175000
b1010 !
b1010 &
1"
#179000
b0 !
b0 &
0$
#180000
0"
#185000
1"
#186000
0$
#190000
0"
#195000
1"
#196000
b0 .
b0 -
1$
#200000
0"
#205000
b1 !
b1 &
1"
#206000
b1 .
b1 -
#210000
0"
#215000
b10 !
b10 &
1"
#216000
b10 .
b10 -
#220000
0"
#225000
b11 !
b11 &
1"
#226000
b11 .
b11 -
#230000
0"
#235000
b100 !
b100 &
1"
#236000
b100 .
b100 -
#240000
0"
#245000
b101 !
b101 &
1"
#246000
b101 .
b101 -
#250000
0"
#255000
b110 !
b110 &
1"
#256000
b110 .
b110 -
#260000
0"
#265000
b111 !
b111 &
1"
#266000
b111 .
b111 -
#270000
0"
#275000
b1000 !
b1000 &
1"
#276000
b1000 .
b1000 -
#280000
0"
#285000
b1001 !
b1001 &
1"
#286000
b1001 .
b1001 -
#290000
0"
#295000
b1010 !
b1010 &
1"
#296000
b1010 .
b1010 -
#300000
0"
#305000
b1011 !
b1011 &
1"
#306000
b1011 .
b1011 -
#310000
0"
#315000
b1100 !
b1100 &
1"
#316000
b1100 .
b1100 -
#320000
0"
#325000
b1101 !
b1101 &
1"
#326000
b1101 .
b1101 -
#330000
0"
#335000
b1110 !
b1110 &
1"
#336000
b1110 .
b1110 -
#340000
0"
#345000
b1111 !
b1111 &
1"
#346000
b1111 .
b1111 -
#350000
0"
#355000
b0 !
b0 &
1"
#356000
b10000 .
b0 -
#360000
0"
#365000
b1 !
b1 &
1"
#366000
b10001 .
b1 -
#370000
0"
#375000
b10 !
b10 &
1"
#380000
0"
#385000
b11 !
b11 &
1"
#390000
0"
#395000
b100 !
b100 &
1"
#400000
0"
#405000
b101 !
b101 &
1"
#410000
0"
#415000
b110 !
b110 &
1"
